{
    "hash": 2657402687, 
    "icon": "/common/destiny_content/icons/ce0dd309f1a2e05a195502505e0ac0ee.png", 
    "index": 0, 
    "name": "weapon_exotic_auto_rifle", 
    "progressionHash": 2657402687, 
    "redacted": false, 
    "repeatLastStep": true, 
    "scope": 2, 
    "steps": [
        {
            "progressTotal": 0, 
            "rewardItems": []
        }, 
        {
            "progressTotal": 3570, 
            "rewardItems": []
        }, 
        {
            "progressTotal": 4284, 
            "rewardItems": []
        }
    ], 
    "visible": true
}