{
    "description": "Complete SRL races on Venus.", 
    "displayName": "Races Finished", 
    "hash": 1005786758, 
    "icon": "/img/destiny_content/records/races_complete.png", 
    "index": 0, 
    "objectives": [
        {
            "objectiveHash": 3770162832
        }
    ], 
    "recordValueUIStyle": "_investment_record_value_ui_style_integer", 
    "rewards": [
        {
            "levelRewarded": 0, 
            "rewardSiteHash": 0, 
            "uiItemHash": 2170625065, 
            "uiItemQuantity": 1
        }, 
        {
            "levelRewarded": 0, 
            "rewardSiteHash": 0, 
            "uiItemHash": 1475579175, 
            "uiItemQuantity": 0
        }
    ]
}