{
    "calcMaxGridLevel": 0, 
    "calcProgressToMaxLevel": 0, 
    "exclusiveSets": [
        {
            "nodeIndexes": [
                0, 
                15
            ]
        }, 
        {
            "nodeIndexes": [
                2, 
                5, 
                6
            ]
        }, 
        {
            "nodeIndexes": [
                7, 
                8, 
                9
            ]
        }
    ], 
    "gridHash": 726179907, 
    "gridLevelPerColumn": 0, 
    "independentNodeIndexes": [
        3, 
        4, 
        10, 
        11, 
        12, 
        13, 
        14, 
        16
    ], 
    "maxGridLevel": 0, 
    "nodes": [
        {
            "autoUnlocks": true, 
            "binaryPairNodeIndex": -1, 
            "column": 1, 
            "exlusiveWithNodes": [
                2658293415
            ], 
            "isRandom": false, 
            "isRandomRepurchasable": false, 
            "lastStepRepeats": false, 
            "nodeHash": 835330335, 
            "nodeIndex": 0, 
            "prerequisiteNodeIndexes": [], 
            "randomStartProgressionBarAtProgression": 11595, 
            "row": 1, 
            "steps": [
                {
                    "activationRequirement": {
                        "gridLevel": 0, 
                        "materialRequirementHashes": []
                    }, 
                    "affectsLevel": false, 
                    "affectsQuality": false, 
                    "canActivateNextStep": false, 
                    "damageType": 3, 
                    "icon": "/common/destiny_content/icons/7809ced245eedd7bb9b96efd9c63595f.png", 
                    "interactionDescription": "Reroll", 
                    "isNextStepRandom": false, 
                    "nextStepIndex": -1, 
                    "nodeStepDescription": "This weapon causes Solar Damage.", 
                    "nodeStepHash": 1975859941, 
                    "nodeStepName": "Solar Damage", 
                    "perkHashes": [
                        233596484
                    ], 
                    "startProgressionBarAtProgress": 0, 
                    "statHashes": [
                        1240592695, 
                        2961396640, 
                        4043523819, 
                        3555269338
                    ], 
                    "stepGroups": {
                        "damageTypes": 4, 
                        "guardianAttributes": 0, 
                        "impactEffects": 0, 
                        "lightAbilities": 0, 
                        "weaponPerformance": 4104
                    }, 
                    "stepIndex": 0, 
                    "truePropertyIndex": 0, 
                    "trueStepIndex": 0
                }
            ]
        }, 
        {
            "autoUnlocks": true, 
            "binaryPairNodeIndex": -1, 
            "column": -1, 
            "exlusiveWithNodes": [], 
            "isRandom": false, 
            "isRandomRepurchasable": false, 
            "lastStepRepeats": false, 
            "nodeHash": 1777049967, 
            "nodeIndex": 1, 
            "prerequisiteNodeIndexes": [], 
            "randomStartProgressionBarAtProgression": 0, 
            "row": 0, 
            "steps": [
                {
                    "activationRequirement": {
                        "gridLevel": 0, 
                        "materialRequirementHashes": []
                    }, 
                    "affectsLevel": false, 
                    "affectsQuality": false, 
                    "canActivateNextStep": false, 
                    "damageType": 0, 
                    "icon": "/common/destiny_content/icons/3d9808e1cbb81ba5f3af7c5e8e8d3625.png", 
                    "interactionDescription": "Reroll", 
                    "isNextStepRandom": false, 
                    "nextStepIndex": -1, 
                    "nodeStepDescription": "This weapon can swap between Arc and Solar damage.", 
                    "nodeStepHash": 1305317488, 
                    "nodeStepName": "Aspect Swap", 
                    "perkHashes": [
                        3787917923
                    ], 
                    "startProgressionBarAtProgress": 0, 
                    "statHashes": [], 
                    "stepIndex": 0, 
                    "truePropertyIndex": 0, 
                    "trueStepIndex": 0
                }
            ]
        }, 
        {
            "autoUnlocks": false, 
            "binaryPairNodeIndex": -1, 
            "column": 2, 
            "exlusiveWithNodes": [
                452419628, 
                1503756812
            ], 
            "isRandom": false, 
            "isRandomRepurchasable": false, 
            "lastStepRepeats": false, 
            "nodeHash": 312682976, 
            "nodeIndex": 2, 
            "prerequisiteNodeIndexes": [], 
            "randomStartProgressionBarAtProgression": 0, 
            "row": 1, 
            "steps": [
                {
                    "activationRequirement": {
                        "gridLevel": 3, 
                        "materialRequirementHashes": [
                            2478960335
                        ]
                    }, 
                    "affectsLevel": false, 
                    "affectsQuality": false, 
                    "canActivateNextStep": false, 
                    "damageType": 0, 
                    "icon": "/common/destiny_content/icons/13578cbb6b939e0b0bd24e37cd940eee.png", 
                    "interactionDescription": "Upgrade", 
                    "isNextStepRandom": false, 
                    "nextStepIndex": -1, 
                    "nodeStepDescription": "Greatly reduced recoil. \nSignificant penalty to range.", 
                    "nodeStepHash": 2443668841, 
                    "nodeStepName": "CQB Ballistics", 
                    "perkHashes": [], 
                    "startProgressionBarAtProgress": 1999, 
                    "statHashes": [
                        1240592695, 
                        155624089
                    ], 
                    "stepGroups": {
                        "damageTypes": 0, 
                        "guardianAttributes": 0, 
                        "impactEffects": 0, 
                        "lightAbilities": 0, 
                        "weaponPerformance": 40
                    }, 
                    "stepIndex": 0, 
                    "truePropertyIndex": 0, 
                    "trueStepIndex": 0
                }
            ]
        }, 
        {
            "autoUnlocks": false, 
            "binaryPairNodeIndex": -1, 
            "column": 4, 
            "exlusiveWithNodes": [], 
            "isRandom": false, 
            "isRandomRepurchasable": false, 
            "lastStepRepeats": false, 
            "nodeHash": 3678843182, 
            "nodeIndex": 3, 
            "prerequisiteNodeIndexes": [], 
            "randomStartProgressionBarAtProgression": 0, 
            "row": 0, 
            "steps": [
                {
                    "activationRequirement": {
                        "gridLevel": 4, 
                        "materialRequirementHashes": [
                            4076686088, 
                            4076686089, 
                            4076686090, 
                            4076686091
                        ]
                    }, 
                    "affectsLevel": false, 
                    "affectsQuality": true, 
                    "canActivateNextStep": false, 
                    "damageType": 0, 
                    "icon": "/common/destiny_content/icons/f402c795b1f64aa1c4ad7be7380a76a8.png", 
                    "interactionDescription": "Upgrade", 
                    "isNextStepRandom": false, 
                    "nextStepIndex": -1, 
                    "nodeStepDescription": "Increases Attack Power, allowing this weapon to cause more damage.", 
                    "nodeStepHash": 2689436406, 
                    "nodeStepName": "Upgrade Damage", 
                    "perkHashes": [], 
                    "startProgressionBarAtProgress": 1999, 
                    "statHashes": [], 
                    "stepIndex": 0, 
                    "truePropertyIndex": 0, 
                    "trueStepIndex": 0
                }
            ]
        }, 
        {
            "autoUnlocks": false, 
            "binaryPairNodeIndex": -1, 
            "column": 3, 
            "exlusiveWithNodes": [], 
            "isRandom": false, 
            "isRandomRepurchasable": false, 
            "lastStepRepeats": false, 
            "nodeHash": 1144665524, 
            "nodeIndex": 4, 
            "prerequisiteNodeIndexes": [], 
            "randomStartProgressionBarAtProgression": 0, 
            "row": 0, 
            "steps": [
                {
                    "activationRequirement": {
                        "gridLevel": 2, 
                        "materialRequirementHashes": [
                            3126742285
                        ]
                    }, 
                    "affectsLevel": false, 
                    "affectsQuality": false, 
                    "canActivateNextStep": false, 
                    "damageType": 0, 
                    "icon": "/common/destiny_content/icons/b77967fb13fec24b41876be617a552cc.png", 
                    "interactionDescription": "Upgrade", 
                    "isNextStepRandom": false, 
                    "nextStepIndex": -1, 
                    "nodeStepDescription": "Kills with this weapon reduce the cooldown of your grenade.", 
                    "nodeStepHash": 3582177736, 
                    "nodeStepName": "Grenadier", 
                    "perkHashes": [
                        3283108368
                    ], 
                    "startProgressionBarAtProgress": 0, 
                    "statHashes": [], 
                    "stepGroups": {
                        "damageTypes": 0, 
                        "guardianAttributes": 0, 
                        "impactEffects": 0, 
                        "lightAbilities": 1, 
                        "weaponPerformance": 0
                    }, 
                    "stepIndex": 0, 
                    "truePropertyIndex": 0, 
                    "trueStepIndex": 0
                }
            ]
        }, 
        {
            "autoUnlocks": true, 
            "binaryPairNodeIndex": -1, 
            "column": 2, 
            "exlusiveWithNodes": [
                312682976, 
                1503756812
            ], 
            "isRandom": false, 
            "isRandomRepurchasable": false, 
            "lastStepRepeats": false, 
            "nodeHash": 452419628, 
            "nodeIndex": 5, 
            "prerequisiteNodeIndexes": [], 
            "randomStartProgressionBarAtProgression": 0, 
            "row": 0, 
            "steps": [
                {
                    "activationRequirement": {
                        "gridLevel": 0, 
                        "materialRequirementHashes": []
                    }, 
                    "affectsLevel": false, 
                    "affectsQuality": false, 
                    "canActivateNextStep": false, 
                    "damageType": 0, 
                    "icon": "/common/destiny_content/icons/0900259064451a76b150b275034fcc70.png", 
                    "interactionDescription": "Upgrade", 
                    "isNextStepRandom": false, 
                    "nextStepIndex": -1, 
                    "nodeStepDescription": "Less recoil. \nPenalty to Impact.", 
                    "nodeStepHash": 3259895023, 
                    "nodeStepName": "Soft Ballistics", 
                    "perkHashes": [
                        2272440440
                    ], 
                    "startProgressionBarAtProgress": 0, 
                    "statHashes": [
                        4043523819, 
                        155624089, 
                        1345609583
                    ], 
                    "stepGroups": {
                        "damageTypes": 0, 
                        "guardianAttributes": 0, 
                        "impactEffects": 0, 
                        "lightAbilities": 0, 
                        "weaponPerformance": 36
                    }, 
                    "stepIndex": 0, 
                    "truePropertyIndex": 0, 
                    "trueStepIndex": 0
                }
            ]
        }, 
        {
            "autoUnlocks": false, 
            "binaryPairNodeIndex": -1, 
            "column": 2, 
            "exlusiveWithNodes": [
                312682976, 
                452419628
            ], 
            "isRandom": false, 
            "isRandomRepurchasable": false, 
            "lastStepRepeats": false, 
            "nodeHash": 1503756812, 
            "nodeIndex": 6, 
            "prerequisiteNodeIndexes": [], 
            "randomStartProgressionBarAtProgression": 0, 
            "row": 2, 
            "steps": [
                {
                    "activationRequirement": {
                        "gridLevel": 4, 
                        "materialRequirementHashes": [
                            2478960335
                        ]
                    }, 
                    "affectsLevel": false, 
                    "affectsQuality": false, 
                    "canActivateNextStep": false, 
                    "damageType": 0, 
                    "icon": "/common/destiny_content/icons/2680442bdadf7143a7d3511073c908f3.png", 
                    "interactionDescription": "Upgrade", 
                    "isNextStepRandom": false, 
                    "nextStepIndex": -1, 
                    "nodeStepDescription": "More predictable recoil. \n Slight boosts to range and Impact. \nMore recoil.", 
                    "nodeStepHash": 423261833, 
                    "nodeStepName": "Linear Compensator", 
                    "perkHashes": [
                        2868044506
                    ], 
                    "startProgressionBarAtProgress": 4398, 
                    "statHashes": [
                        1240592695, 
                        4043523819, 
                        2715839340, 
                        155624089, 
                        1345609583
                    ], 
                    "stepGroups": {
                        "damageTypes": 0, 
                        "guardianAttributes": 0, 
                        "impactEffects": 0, 
                        "lightAbilities": 0, 
                        "weaponPerformance": 44
                    }, 
                    "stepIndex": 0, 
                    "truePropertyIndex": 0, 
                    "trueStepIndex": 0
                }
            ]
        }, 
        {
            "autoUnlocks": false, 
            "binaryPairNodeIndex": -1, 
            "column": 5, 
            "exlusiveWithNodes": [
                2947148901, 
                2133033345
            ], 
            "isRandom": false, 
            "isRandomRepurchasable": false, 
            "lastStepRepeats": false, 
            "nodeHash": 3359939809, 
            "nodeIndex": 7, 
            "prerequisiteNodeIndexes": [], 
            "randomStartProgressionBarAtProgression": 0, 
            "row": 0, 
            "steps": [
                {
                    "activationRequirement": {
                        "gridLevel": 5, 
                        "materialRequirementHashes": [
                            3126742285
                        ]
                    }, 
                    "affectsLevel": false, 
                    "affectsQuality": false, 
                    "canActivateNextStep": false, 
                    "damageType": 0, 
                    "icon": "/common/destiny_content/icons/b00999cbf37735d7f12ecfa49670cb60.png", 
                    "interactionDescription": "Upgrade", 
                    "isNextStepRandom": false, 
                    "nextStepIndex": -1, 
                    "nodeStepDescription": "Increases magazine size.", 
                    "nodeStepHash": 1670053670, 
                    "nodeStepName": "Enhanced Battery", 
                    "perkHashes": [], 
                    "startProgressionBarAtProgress": 6797, 
                    "statHashes": [
                        3871231066
                    ], 
                    "stepGroups": {
                        "damageTypes": 0, 
                        "guardianAttributes": 0, 
                        "impactEffects": 0, 
                        "lightAbilities": 0, 
                        "weaponPerformance": 512
                    }, 
                    "stepIndex": 0, 
                    "truePropertyIndex": 0, 
                    "trueStepIndex": 0
                }
            ]
        }, 
        {
            "autoUnlocks": false, 
            "binaryPairNodeIndex": -1, 
            "column": 5, 
            "exlusiveWithNodes": [
                3359939809, 
                2133033345
            ], 
            "isRandom": false, 
            "isRandomRepurchasable": false, 
            "lastStepRepeats": false, 
            "nodeHash": 2947148901, 
            "nodeIndex": 8, 
            "prerequisiteNodeIndexes": [], 
            "randomStartProgressionBarAtProgression": 0, 
            "row": 1, 
            "steps": [
                {
                    "activationRequirement": {
                        "gridLevel": 6, 
                        "materialRequirementHashes": [
                            3126742285
                        ]
                    }, 
                    "affectsLevel": false, 
                    "affectsQuality": false, 
                    "canActivateNextStep": false, 
                    "damageType": 0, 
                    "icon": "/common/destiny_content/icons/2e9d474c29918d47b5cd0f495f891677.png", 
                    "interactionDescription": "Upgrade", 
                    "isNextStepRandom": false, 
                    "nextStepIndex": -1, 
                    "nodeStepDescription": "When held, this weapon grants +2 character Agility.", 
                    "nodeStepHash": 1821665467, 
                    "nodeStepName": "Lightweight", 
                    "perkHashes": [
                        890364775
                    ], 
                    "startProgressionBarAtProgress": 9196, 
                    "statHashes": [], 
                    "stepGroups": {
                        "damageTypes": 0, 
                        "guardianAttributes": 1, 
                        "impactEffects": 0, 
                        "lightAbilities": 0, 
                        "weaponPerformance": 0
                    }, 
                    "stepIndex": 0, 
                    "truePropertyIndex": 0, 
                    "trueStepIndex": 0
                }
            ]
        }, 
        {
            "autoUnlocks": false, 
            "binaryPairNodeIndex": -1, 
            "column": 5, 
            "exlusiveWithNodes": [
                3359939809, 
                2947148901
            ], 
            "isRandom": false, 
            "isRandomRepurchasable": false, 
            "lastStepRepeats": false, 
            "nodeHash": 2133033345, 
            "nodeIndex": 9, 
            "prerequisiteNodeIndexes": [], 
            "randomStartProgressionBarAtProgression": 0, 
            "row": 2, 
            "steps": [
                {
                    "activationRequirement": {
                        "gridLevel": 7, 
                        "materialRequirementHashes": [
                            3126742285
                        ]
                    }, 
                    "affectsLevel": false, 
                    "affectsQuality": false, 
                    "canActivateNextStep": false, 
                    "damageType": 0, 
                    "icon": "/common/destiny_content/icons/b662a95d1b2354a25e58f096f7385441.png", 
                    "interactionDescription": "Upgrade", 
                    "isNextStepRandom": false, 
                    "nextStepIndex": -1, 
                    "nodeStepDescription": "Aiming this weapon is incredibly fast.", 
                    "nodeStepHash": 2479685401, 
                    "nodeStepName": "Snapshot", 
                    "perkHashes": [
                        1563623317
                    ], 
                    "startProgressionBarAtProgress": 11595, 
                    "statHashes": [], 
                    "stepGroups": {
                        "damageTypes": 0, 
                        "guardianAttributes": 0, 
                        "impactEffects": 0, 
                        "lightAbilities": 0, 
                        "weaponPerformance": 64
                    }, 
                    "stepIndex": 0, 
                    "truePropertyIndex": 0, 
                    "trueStepIndex": 0
                }
            ]
        }, 
        {
            "autoUnlocks": false, 
            "binaryPairNodeIndex": -1, 
            "column": 8, 
            "exlusiveWithNodes": [], 
            "isRandom": false, 
            "isRandomRepurchasable": false, 
            "lastStepRepeats": false, 
            "nodeHash": 527202181, 
            "nodeIndex": 10, 
            "prerequisiteNodeIndexes": [], 
            "randomStartProgressionBarAtProgression": 0, 
            "row": 0, 
            "steps": [
                {
                    "activationRequirement": {
                        "gridLevel": 9, 
                        "materialRequirementHashes": [
                            3984507349, 
                            3984507348, 
                            3984507351, 
                            3984507350
                        ]
                    }, 
                    "affectsLevel": false, 
                    "affectsQuality": true, 
                    "canActivateNextStep": false, 
                    "damageType": 0, 
                    "icon": "/common/destiny_content/icons/f402c795b1f64aa1c4ad7be7380a76a8.png", 
                    "interactionDescription": "Upgrade", 
                    "isNextStepRandom": false, 
                    "nextStepIndex": -1, 
                    "nodeStepDescription": "Increases Attack Power, allowing this weapon to cause more damage.", 
                    "nodeStepHash": 2689436406, 
                    "nodeStepName": "Upgrade Damage", 
                    "perkHashes": [], 
                    "startProgressionBarAtProgress": 16393, 
                    "statHashes": [], 
                    "stepIndex": 0, 
                    "truePropertyIndex": 0, 
                    "trueStepIndex": 0
                }
            ]
        }, 
        {
            "autoUnlocks": false, 
            "binaryPairNodeIndex": -1, 
            "column": 8, 
            "exlusiveWithNodes": [], 
            "isRandom": false, 
            "isRandomRepurchasable": false, 
            "lastStepRepeats": false, 
            "nodeHash": 527055148, 
            "nodeIndex": 11, 
            "prerequisiteNodeIndexes": [], 
            "randomStartProgressionBarAtProgression": 0, 
            "row": 1, 
            "steps": [
                {
                    "activationRequirement": {
                        "gridLevel": 10, 
                        "materialRequirementHashes": [
                            3984507349, 
                            3984507348, 
                            3984507351, 
                            3984507350
                        ]
                    }, 
                    "affectsLevel": false, 
                    "affectsQuality": true, 
                    "canActivateNextStep": false, 
                    "damageType": 0, 
                    "icon": "/common/destiny_content/icons/f402c795b1f64aa1c4ad7be7380a76a8.png", 
                    "interactionDescription": "Upgrade", 
                    "isNextStepRandom": false, 
                    "nextStepIndex": -1, 
                    "nodeStepDescription": "Increases Attack Power, allowing this weapon to cause more damage.", 
                    "nodeStepHash": 2689436406, 
                    "nodeStepName": "Upgrade Damage", 
                    "perkHashes": [], 
                    "startProgressionBarAtProgress": 18792, 
                    "statHashes": [], 
                    "stepIndex": 0, 
                    "truePropertyIndex": 0, 
                    "trueStepIndex": 0
                }
            ]
        }, 
        {
            "autoUnlocks": false, 
            "binaryPairNodeIndex": -1, 
            "column": 8, 
            "exlusiveWithNodes": [], 
            "isRandom": false, 
            "isRandomRepurchasable": false, 
            "lastStepRepeats": false, 
            "nodeHash": 1601264051, 
            "nodeIndex": 12, 
            "prerequisiteNodeIndexes": [], 
            "randomStartProgressionBarAtProgression": 0, 
            "row": 2, 
            "steps": [
                {
                    "activationRequirement": {
                        "gridLevel": 11, 
                        "materialRequirementHashes": [
                            3984507349, 
                            3984507348, 
                            3984507351, 
                            3984507350
                        ]
                    }, 
                    "affectsLevel": false, 
                    "affectsQuality": true, 
                    "canActivateNextStep": false, 
                    "damageType": 0, 
                    "icon": "/common/destiny_content/icons/f402c795b1f64aa1c4ad7be7380a76a8.png", 
                    "interactionDescription": "Upgrade", 
                    "isNextStepRandom": false, 
                    "nextStepIndex": -1, 
                    "nodeStepDescription": "Increases Attack Power, allowing this weapon to cause more damage.", 
                    "nodeStepHash": 2689436406, 
                    "nodeStepName": "Upgrade Damage", 
                    "perkHashes": [], 
                    "startProgressionBarAtProgress": 21191, 
                    "statHashes": [], 
                    "stepIndex": 0, 
                    "truePropertyIndex": 0, 
                    "trueStepIndex": 0
                }
            ]
        }, 
        {
            "autoUnlocks": false, 
            "binaryPairNodeIndex": -1, 
            "column": 7, 
            "exlusiveWithNodes": [], 
            "isRandom": false, 
            "isRandomRepurchasable": false, 
            "lastStepRepeats": false, 
            "nodeHash": 486779184, 
            "nodeIndex": 13, 
            "prerequisiteNodeIndexes": [], 
            "randomStartProgressionBarAtProgression": 0, 
            "row": 0, 
            "steps": [
                {
                    "activationRequirement": {
                        "gridLevel": 8, 
                        "materialRequirementHashes": [
                            3984475350, 
                            3984475351, 
                            3984475348, 
                            3984475349
                        ]
                    }, 
                    "affectsLevel": false, 
                    "affectsQuality": true, 
                    "canActivateNextStep": false, 
                    "damageType": 0, 
                    "icon": "/common/destiny_content/icons/f402c795b1f64aa1c4ad7be7380a76a8.png", 
                    "interactionDescription": "Upgrade", 
                    "isNextStepRandom": false, 
                    "nextStepIndex": -1, 
                    "nodeStepDescription": "Increases Attack Power, allowing this weapon to cause more damage.", 
                    "nodeStepHash": 2689436406, 
                    "nodeStepName": "Upgrade Damage", 
                    "perkHashes": [], 
                    "startProgressionBarAtProgress": 11595, 
                    "statHashes": [], 
                    "stepIndex": 0, 
                    "truePropertyIndex": 0, 
                    "trueStepIndex": 0
                }
            ]
        }, 
        {
            "autoUnlocks": false, 
            "binaryPairNodeIndex": -1, 
            "column": 6, 
            "exlusiveWithNodes": [], 
            "isRandom": false, 
            "isRandomRepurchasable": false, 
            "lastStepRepeats": false, 
            "nodeHash": 3373417848, 
            "nodeIndex": 14, 
            "prerequisiteNodeIndexes": [], 
            "randomStartProgressionBarAtProgression": 0, 
            "row": 0, 
            "steps": [
                {
                    "activationRequirement": {
                        "gridLevel": 6, 
                        "materialRequirementHashes": [
                            391095254
                        ]
                    }, 
                    "affectsLevel": false, 
                    "affectsQuality": false, 
                    "canActivateNextStep": false, 
                    "damageType": 0, 
                    "icon": "/common/destiny_content/icons/09ddb4a499219da2ec4c3600d4aebf95.png", 
                    "interactionDescription": "Upgrade", 
                    "isNextStepRandom": false, 
                    "nextStepIndex": -1, 
                    "nodeStepDescription": "Slide further while this weapon is equipped.", 
                    "nodeStepHash": 1422049438, 
                    "nodeStepName": "Kneepads", 
                    "perkHashes": [], 
                    "startProgressionBarAtProgress": 9196, 
                    "statHashes": [], 
                    "stepIndex": 0, 
                    "truePropertyIndex": 0, 
                    "trueStepIndex": 0
                }
            ]
        }, 
        {
            "autoUnlocks": true, 
            "binaryPairNodeIndex": -1, 
            "column": 1, 
            "exlusiveWithNodes": [
                835330335
            ], 
            "isRandom": false, 
            "isRandomRepurchasable": false, 
            "lastStepRepeats": false, 
            "nodeHash": 2658293415, 
            "nodeIndex": 15, 
            "prerequisiteNodeIndexes": [], 
            "randomStartProgressionBarAtProgression": 0, 
            "row": 0, 
            "steps": [
                {
                    "activationRequirement": {
                        "gridLevel": 0, 
                        "materialRequirementHashes": []
                    }, 
                    "affectsLevel": false, 
                    "affectsQuality": false, 
                    "canActivateNextStep": false, 
                    "damageType": 2, 
                    "icon": "/common/destiny_content/icons/e49f38e9297093c838f1626225e08029.png", 
                    "interactionDescription": "Reroll", 
                    "isNextStepRandom": false, 
                    "nextStepIndex": -1, 
                    "nodeStepDescription": "This weapon causes Arc Damage.", 
                    "nodeStepHash": 2688431654, 
                    "nodeStepName": "Arc Damage", 
                    "perkHashes": [
                        839929915
                    ], 
                    "startProgressionBarAtProgress": 0, 
                    "statHashes": [
                        1240592695, 
                        2961396640, 
                        4043523819, 
                        4188031367
                    ], 
                    "stepGroups": {
                        "damageTypes": 2, 
                        "guardianAttributes": 0, 
                        "impactEffects": 0, 
                        "lightAbilities": 0, 
                        "weaponPerformance": 4232
                    }, 
                    "stepIndex": 0, 
                    "truePropertyIndex": 0, 
                    "trueStepIndex": 0
                }
            ]
        }, 
        {
            "autoUnlocks": false, 
            "binaryPairNodeIndex": -1, 
            "column": 0, 
            "exlusiveWithNodes": [], 
            "isRandom": false, 
            "isRandomRepurchasable": false, 
            "lastStepRepeats": false, 
            "nodeHash": 402935547, 
            "nodeIndex": 16, 
            "prerequisiteNodeIndexes": [], 
            "randomStartProgressionBarAtProgression": 0, 
            "row": 2, 
            "steps": [
                {
                    "activationRequirement": {
                        "gridLevel": 0, 
                        "materialRequirementHashes": [
                            433793496
                        ]
                    }, 
                    "affectsLevel": false, 
                    "affectsQuality": false, 
                    "canActivateNextStep": false, 
                    "damageType": 0, 
                    "icon": "/common/destiny_content/icons/f7b6c0a665d68771896beee11a18f2ee.png", 
                    "interactionDescription": "Upgrade", 
                    "isNextStepRandom": false, 
                    "nextStepIndex": -1, 
                    "nodeStepDescription": "Increases the Attack value of this weapon to the highest available in Year 1.", 
                    "nodeStepHash": 1920788875, 
                    "nodeStepName": "Ascend", 
                    "perkHashes": [], 
                    "startProgressionBarAtProgress": 0, 
                    "statHashes": [], 
                    "stepIndex": 0, 
                    "truePropertyIndex": 0, 
                    "trueStepIndex": 0
                }
            ]
        }
    ], 
    "progressionHash": 3605101483
}