{
    "activityDescription": "Launches a random Nightfall strike.", 
    "activityHash": 1749151224, 
    "activityLevel": 42, 
    "activityName": "Vanguard Nightfall", 
    "activityPower": 0.0, 
    "activityTypeHash": 575572995, 
    "completionFlagHash": 0, 
    "destinationHash": 2512542997, 
    "hash": 1749151224, 
    "icon": "/img/theme/destiny/icons/node_strike_nightfall.png", 
    "index": 0, 
    "isPlaylist": true, 
    "maxParty": 3, 
    "maxPlayers": 3, 
    "minParty": 1, 
    "pgcrImage": "/img/theme/destiny/bgs/pgcrs/placeholder.jpg", 
    "placeHash": 3747705955, 
    "releaseIcon": "/common/destiny_content/icons/9f4f5477db6e44dce2b24db780c953ef.png", 
    "releaseTime": 0, 
    "rewards": [
        {
            "rewardItems": [
                {
                    "itemHash": 3747303650, 
                    "value": 0
                }
            ]
        }
    ], 
    "skulls": [
        {
            "description": "Heavily shielded and highly aggressive enemies appear in great numbers.", 
            "displayName": "Epic", 
            "icon": "/common/destiny_content/icons/9cff0e0a4da92e3b2e0daf3248af4892.png"
        }, 
        {
            "description": "Arc Damage from any source is greatly increased.", 
            "displayName": "Arc Burn", 
            "icon": "/common/destiny_content/icons/6647a7b0bc44c71625deb02d85fbfda6.png"
        }, 
        {
            "description": "Solar damage from any source is greatly increased.", 
            "displayName": "Solar Burn", 
            "icon": "/common/destiny_content/icons/3bbcf4e46a5b89d9d95afda24a62f880.png"
        }, 
        {
            "description": "Void damage from any source is greatly increased.", 
            "displayName": "Void Burn", 
            "icon": "/common/destiny_content/icons/1bebb5ad0a63199b15e6d6d8b74c9a5a.png"
        }, 
        {
            "description": "Minions of the Darkness won't flinch, even after massive damage.", 
            "displayName": "Berserk", 
            "icon": "/common/destiny_content/icons/f77b9bef16960db1b8ecdba74707651f.png"
        }, 
        {
            "description": "Guardian melee damage is greatly increased.", 
            "displayName": "Brawler", 
            "icon": "/common/destiny_content/icons/294c758af84fef41301c5c929461f05a.png"
        }, 
        {
            "description": "Minions of the Darkness deal much more melee damage.", 
            "displayName": "Lightswitch", 
            "icon": "/common/destiny_content/icons/ab72e94c371189667feb93c1c6fcc1d7.png"
        }, 
        {
            "description": "Special Weapon damage is favored.", 
            "displayName": "Specialist", 
            "icon": "/common/destiny_content/icons/34bbc0c4bb4252f039cac2f90c92069a.png"
        }, 
        {
            "description": "Primary Weapon damage is favored.", 
            "displayName": "Small Arms", 
            "icon": "/common/destiny_content/icons/f023656edc58bfa14e38db3e4e94e580.png"
        }, 
        {
            "description": "No ammo drops for your equipped weapon.", 
            "displayName": "Juggler", 
            "icon": "/common/destiny_content/icons/15ebec421611e2d360a8f632ff3d31c6.png"
        }, 
        {
            "description": "Players take more damage while airborne.", 
            "displayName": "Grounded", 
            "icon": "/common/destiny_content/icons/f080b45f4bd03b010930b58f796bbad0.png"
        }, 
        {
            "description": "Enemies fire more frequently and more accurately.", 
            "displayName": "Bloodthirsty", 
            "icon": "/common/destiny_content/icons/3778ef9b61f33157e13804383dabfff5.png"
        }, 
        {
            "description": "Player radar is disabled.", 
            "displayName": "Chaff", 
            "icon": "/common/destiny_content/icons/bd9097c50ecd12dbe6d9f90f2620a3ef.png"
        }, 
        {
            "description": "Some enemy squads have been fortified with additional reinforcements.", 
            "displayName": "Fresh Troops", 
            "icon": "/common/destiny_content/icons/8bed105e53d3cf156779c641dbc365a9.png"
        }, 
        {
            "description": "More enemies have shields.", 
            "displayName": "Ironclad", 
            "icon": "/common/destiny_content/icons/18947f8b99abe08172a21408b7d40279.png"
        }, 
        {
            "description": "Enemy shields are resistant to all unmatched Elemental Damage.", 
            "displayName": "Match Game", 
            "icon": "/common/destiny_content/icons/20fcb3100588f8155eae0c3253c769f1.png"
        }, 
        {
            "description": "Players deal more damage while in the air.", 
            "displayName": "Airborne", 
            "icon": "/common/destiny_content/icons/cd6c4f87d13103f484ec9c17a3638a25.png"
        }, 
        {
            "description": "Grenade recharge rate is greatly increased.", 
            "displayName": "Catapult", 
            "icon": "/common/destiny_content/icons/d878af5b6cf0500a3d3a7502adaa5d5a.png"
        }, 
        {
            "description": "Guardian shields are increased but do not replenish.", 
            "displayName": "Exposure", 
            "icon": "/common/destiny_content/icons/07131ff77bff792e91862738915bedb7.png"
        }, 
        {
            "description": "Recharge of abilities is significantly reduced.", 
            "displayName": "Trickle", 
            "icon": "/common/destiny_content/icons/3974e0d1ea90a9b6473fd3b3722a55dd.png"
        }
    ], 
    "tier": 1
}