{
    "cardDescription": "The Maraid, Book VIII, Chapter 9 <br/><br/>\nAbstract:<br/>\nVariks of the House of Judgment declared Queen Mara Sov the new Kell of Wolves, and advised those captured at Cybele to serve her. The first among these to pledge their loyalty to the Queen was one called Saviks, who was given the honor of serving in the Queen&#39;s throne room, to the right of the Queen herself.<br/><br/>\n[See Book IX, Chapter 3, subsection &quot;The Queenbreakers.&quot;]", 
    "cardId": 688120, 
    "cardIntro": "<b>STATUS: Escaped from the Prison of Elders; AT LARGE</b>", 
    "cardName": "WANTED: Saviks, Queenbreaker", 
    "highResolution": {
        "image": {
            "rect": {
                "height": 728, 
                "width": 560, 
                "x": 0, 
                "y": 0
            }, 
            "sheetPath": "/common/destiny_content/grimoire/hr_images/688120_cee3b410ab58ced2e1c1b6114cd1a5f9.jpg", 
            "sheetSize": {
                "height": 728, 
                "width": 560, 
                "x": 0, 
                "y": 0
            }
        }, 
        "smallImage": {
            "rect": {
                "height": 145, 
                "width": 145, 
                "x": 1595, 
                "y": 0
            }, 
            "sheetPath": "/common/destiny_content/grimoire/hr_images/FallenHunted-csprites-sm_fa2f1e42952bfc3ed3023435b91c0e13.jpg", 
            "sheetSize": {
                "height": 290, 
                "width": 1885, 
                "x": 0, 
                "y": 0
            }
        }
    }, 
    "normalResolution": {
        "image": {
            "rect": {
                "height": 419, 
                "width": 323, 
                "x": 1615, 
                "y": 419
            }, 
            "sheetPath": "/common/destiny_content/grimoire/images/FallenHunted-csprites_80cfa00ffad1c606fe3a2a3f799e1434.jpg", 
            "sheetSize": {
                "height": 2095, 
                "width": 1938, 
                "x": 0, 
                "y": 0
            }
        }, 
        "smallImage": {
            "rect": {
                "height": 83, 
                "width": 83, 
                "x": 913, 
                "y": 0
            }, 
            "sheetPath": "/common/destiny_content/grimoire/images/FallenHunted-csprites-sm_00301f1a035152c9765c67fef6dab66d.jpg", 
            "sheetSize": {
                "height": 249, 
                "width": 996, 
                "x": 0, 
                "y": 0
            }
        }
    }, 
    "points": 10, 
    "rarity": 2, 
    "unlockFlagHash": 0, 
    "unlockHowToText": "Unlock this card by playing Destiny."
}