{
    "actionName": "Dismantle", 
    "allowActions": true, 
    "bountyResetUnlockHash": 0, 
    "bucketTypeHash": 953998645, 
    "classType": 3, 
    "damageTypes": [
        3
    ], 
    "deleteOnAction": true, 
    "equippable": true, 
    "equippingBlock": {
        "arrangements": [
            {
                "classHash": 0, 
                "gearArtArrangementIndex": 3484
            }
        ], 
        "customDyeExpression": {
            "steps": []
        }, 
        "customDyes": [], 
        "defaultDyes": [], 
        "equipmentSlotHash": 953998645, 
        "gearArtArrangementIndex": 3484, 
        "lockedDyes": [
            {
                "channelHash": 1667433279, 
                "dyeHash": 3737404787
            }, 
            {
                "channelHash": 1667433278, 
                "dyeHash": 1358884908
            }
        ], 
        "weaponPatternHash": 3715563181, 
        "weaponSandboxPatternIndex": 17
    }, 
    "exclusive": 0, 
    "hasAction": true, 
    "hasGeometry": true, 
    "hasIcon": true, 
    "hash": 2808364179, 
    "icon": "/common/destiny_content/icons/90839e29a9039a599dc5f64b0d0ae55e.jpg", 
    "index": 0, 
    "instanced": true, 
    "itemCategoryHashes": [
        1, 
        4, 
        13
    ], 
    "itemDescription": "Burn the world. Burn it all.", 
    "itemHash": 2808364179, 
    "itemIndex": 0, 
    "itemLevels": [
        0
    ], 
    "itemName": "Dragon's Breath", 
    "itemSubType": 10, 
    "itemType": 3, 
    "itemTypeName": "Rocket Launcher", 
    "maxStackSize": 1, 
    "needsFullCompletion": false, 
    "nonTransferrable": false, 
    "objectiveHashes": [], 
    "perkHashes": [], 
    "primaryBaseStatHash": 368428387, 
    "qualityLevel": 0, 
    "questTrackingUnlockValueHash": 0, 
    "questlineItemHash": 0, 
    "redacted": false, 
    "rewardItemHash": 0, 
    "secondaryIcon": "/img/misc/missing_icon.png", 
    "setItemHashes": [], 
    "showActiveNodesInTooltip": false, 
    "sourceHashes": [
        3147905712, 
        460228854, 
        941581325, 
        113998144, 
        3551688287, 
        3413298620
    ], 
    "sources": [
        {
            "computedStats": {
                "1345609583": {
                    "maximum": 25, 
                    "minimum": 15, 
                    "statHash": 1345609583, 
                    "value": 25
                }, 
                "155624089": {
                    "maximum": 76, 
                    "minimum": 58, 
                    "statHash": 155624089, 
                    "value": 66
                }, 
                "1931675084": {
                    "maximum": 70, 
                    "minimum": 70, 
                    "statHash": 1931675084, 
                    "value": 70
                }, 
                "2391494160": {
                    "maximum": 48, 
                    "minimum": 45, 
                    "statHash": 2391494160, 
                    "value": 45
                }, 
                "2523465841": {
                    "maximum": 45, 
                    "minimum": 30, 
                    "statHash": 2523465841, 
                    "value": 30
                }, 
                "2715839340": {
                    "maximum": 70, 
                    "minimum": 50, 
                    "statHash": 2715839340, 
                    "value": 50
                }, 
                "3555269338": {
                    "maximum": 20, 
                    "minimum": 20, 
                    "statHash": 3555269338, 
                    "value": 20
                }, 
                "3614673599": {
                    "maximum": 60, 
                    "minimum": 60, 
                    "statHash": 3614673599, 
                    "value": 60
                }, 
                "368428387": {
                    "maximum": 400, 
                    "minimum": 380, 
                    "statHash": 368428387, 
                    "value": 380
                }, 
                "3871231066": {
                    "maximum": 1, 
                    "minimum": 1, 
                    "statHash": 3871231066, 
                    "value": 1
                }, 
                "4188031367": {
                    "maximum": 59, 
                    "minimum": 52, 
                    "statHash": 4188031367, 
                    "value": 52
                }, 
                "4284893193": {
                    "maximum": 18, 
                    "minimum": 18, 
                    "statHash": 4284893193, 
                    "value": 18
                }, 
                "943549884": {
                    "maximum": 25, 
                    "minimum": 25, 
                    "statHash": 943549884, 
                    "value": 25
                }
            }, 
            "exclusivity": 0, 
            "expansionIndex": 0, 
            "level": 58, 
            "maxLevelRequired": 40, 
            "maxQuality": 20, 
            "minLevelRequired": 40, 
            "minQuality": 0, 
            "sourceHashes": [
                3147905712, 
                460228854
            ]
        }, 
        {
            "computedStats": {
                "1345609583": {
                    "maximum": 25, 
                    "minimum": 15, 
                    "statHash": 1345609583, 
                    "value": 25
                }, 
                "155624089": {
                    "maximum": 76, 
                    "minimum": 58, 
                    "statHash": 155624089, 
                    "value": 66
                }, 
                "1931675084": {
                    "maximum": 70, 
                    "minimum": 70, 
                    "statHash": 1931675084, 
                    "value": 70
                }, 
                "2391494160": {
                    "maximum": 46, 
                    "minimum": 43, 
                    "statHash": 2391494160, 
                    "value": 43
                }, 
                "2523465841": {
                    "maximum": 45, 
                    "minimum": 30, 
                    "statHash": 2523465841, 
                    "value": 30
                }, 
                "2715839340": {
                    "maximum": 70, 
                    "minimum": 50, 
                    "statHash": 2715839340, 
                    "value": 50
                }, 
                "3555269338": {
                    "maximum": 20, 
                    "minimum": 20, 
                    "statHash": 3555269338, 
                    "value": 20
                }, 
                "3614673599": {
                    "maximum": 60, 
                    "minimum": 60, 
                    "statHash": 3614673599, 
                    "value": 60
                }, 
                "368428387": {
                    "maximum": 385, 
                    "minimum": 365, 
                    "statHash": 368428387, 
                    "value": 365
                }, 
                "3871231066": {
                    "maximum": 1, 
                    "minimum": 1, 
                    "statHash": 3871231066, 
                    "value": 1
                }, 
                "4188031367": {
                    "maximum": 59, 
                    "minimum": 52, 
                    "statHash": 4188031367, 
                    "value": 52
                }, 
                "4284893193": {
                    "maximum": 18, 
                    "minimum": 18, 
                    "statHash": 4284893193, 
                    "value": 18
                }, 
                "943549884": {
                    "maximum": 25, 
                    "minimum": 25, 
                    "statHash": 943549884, 
                    "value": 25
                }
            }, 
            "exclusivity": 0, 
            "expansionIndex": 0, 
            "level": 56, 
            "maxLevelRequired": 40, 
            "maxQuality": 25, 
            "minLevelRequired": 40, 
            "minQuality": 5, 
            "sourceHashes": [
                3147905712, 
                460228854
            ]
        }, 
        {
            "computedStats": {
                "1345609583": {
                    "maximum": 25, 
                    "minimum": 15, 
                    "statHash": 1345609583, 
                    "value": 25
                }, 
                "155624089": {
                    "maximum": 76, 
                    "minimum": 58, 
                    "statHash": 155624089, 
                    "value": 66
                }, 
                "1931675084": {
                    "maximum": 70, 
                    "minimum": 70, 
                    "statHash": 1931675084, 
                    "value": 70
                }, 
                "2391494160": {
                    "maximum": 42, 
                    "minimum": 42, 
                    "statHash": 2391494160, 
                    "value": 42
                }, 
                "2523465841": {
                    "maximum": 45, 
                    "minimum": 30, 
                    "statHash": 2523465841, 
                    "value": 30
                }, 
                "2715839340": {
                    "maximum": 70, 
                    "minimum": 50, 
                    "statHash": 2715839340, 
                    "value": 50
                }, 
                "3555269338": {
                    "maximum": 20, 
                    "minimum": 20, 
                    "statHash": 3555269338, 
                    "value": 20
                }, 
                "3614673599": {
                    "maximum": 60, 
                    "minimum": 60, 
                    "statHash": 3614673599, 
                    "value": 60
                }, 
                "368428387": {
                    "maximum": 350, 
                    "minimum": 350, 
                    "statHash": 368428387, 
                    "value": 350
                }, 
                "3871231066": {
                    "maximum": 1, 
                    "minimum": 1, 
                    "statHash": 3871231066, 
                    "value": 1
                }, 
                "4188031367": {
                    "maximum": 59, 
                    "minimum": 52, 
                    "statHash": 4188031367, 
                    "value": 52
                }, 
                "4284893193": {
                    "maximum": 18, 
                    "minimum": 18, 
                    "statHash": 4284893193, 
                    "value": 18
                }, 
                "943549884": {
                    "maximum": 25, 
                    "minimum": 25, 
                    "statHash": 943549884, 
                    "value": 25
                }
            }, 
            "exclusivity": 0, 
            "expansionIndex": 0, 
            "level": 55, 
            "maxLevelRequired": 40, 
            "maxQuality": 0, 
            "minLevelRequired": 40, 
            "minQuality": 0, 
            "sourceHashes": [
                941581325, 
                460228854
            ]
        }, 
        {
            "computedStats": {
                "1345609583": {
                    "maximum": 25, 
                    "minimum": 15, 
                    "statHash": 1345609583, 
                    "value": 25
                }, 
                "155624089": {
                    "maximum": 76, 
                    "minimum": 58, 
                    "statHash": 155624089, 
                    "value": 66
                }, 
                "1931675084": {
                    "maximum": 70, 
                    "minimum": 70, 
                    "statHash": 1931675084, 
                    "value": 70
                }, 
                "2391494160": {
                    "maximum": 48, 
                    "minimum": 36, 
                    "statHash": 2391494160, 
                    "value": 36
                }, 
                "2523465841": {
                    "maximum": 45, 
                    "minimum": 30, 
                    "statHash": 2523465841, 
                    "value": 30
                }, 
                "2715839340": {
                    "maximum": 70, 
                    "minimum": 50, 
                    "statHash": 2715839340, 
                    "value": 50
                }, 
                "3555269338": {
                    "maximum": 20, 
                    "minimum": 20, 
                    "statHash": 3555269338, 
                    "value": 20
                }, 
                "3614673599": {
                    "maximum": 60, 
                    "minimum": 60, 
                    "statHash": 3614673599, 
                    "value": 60
                }, 
                "368428387": {
                    "maximum": 400, 
                    "minimum": 300, 
                    "statHash": 368428387, 
                    "value": 300
                }, 
                "3871231066": {
                    "maximum": 1, 
                    "minimum": 1, 
                    "statHash": 3871231066, 
                    "value": 1
                }, 
                "4188031367": {
                    "maximum": 59, 
                    "minimum": 52, 
                    "statHash": 4188031367, 
                    "value": 52
                }, 
                "4284893193": {
                    "maximum": 18, 
                    "minimum": 18, 
                    "statHash": 4284893193, 
                    "value": 18
                }, 
                "943549884": {
                    "maximum": 25, 
                    "minimum": 25, 
                    "statHash": 943549884, 
                    "value": 25
                }
            }, 
            "exclusivity": 0, 
            "expansionIndex": 0, 
            "level": 50, 
            "maxLevelRequired": 40, 
            "maxQuality": 100, 
            "minLevelRequired": 40, 
            "minQuality": 0, 
            "sourceHashes": [
                113998144, 
                3551688287, 
                3413298620, 
                460228854
            ]
        }, 
        {
            "computedStats": {
                "1345609583": {
                    "maximum": 25, 
                    "minimum": 15, 
                    "statHash": 1345609583, 
                    "value": 25
                }, 
                "155624089": {
                    "maximum": 76, 
                    "minimum": 58, 
                    "statHash": 155624089, 
                    "value": 66
                }, 
                "1931675084": {
                    "maximum": 70, 
                    "minimum": 70, 
                    "statHash": 1931675084, 
                    "value": 70
                }, 
                "2391494160": {
                    "maximum": 33, 
                    "minimum": 33, 
                    "statHash": 2391494160, 
                    "value": 33
                }, 
                "2523465841": {
                    "maximum": 45, 
                    "minimum": 30, 
                    "statHash": 2523465841, 
                    "value": 30
                }, 
                "2715839340": {
                    "maximum": 70, 
                    "minimum": 50, 
                    "statHash": 2715839340, 
                    "value": 50
                }, 
                "3555269338": {
                    "maximum": 20, 
                    "minimum": 20, 
                    "statHash": 3555269338, 
                    "value": 20
                }, 
                "3614673599": {
                    "maximum": 60, 
                    "minimum": 60, 
                    "statHash": 3614673599, 
                    "value": 60
                }, 
                "368428387": {
                    "maximum": 280, 
                    "minimum": 280, 
                    "statHash": 368428387, 
                    "value": 280
                }, 
                "3871231066": {
                    "maximum": 1, 
                    "minimum": 1, 
                    "statHash": 3871231066, 
                    "value": 1
                }, 
                "4188031367": {
                    "maximum": 59, 
                    "minimum": 52, 
                    "statHash": 4188031367, 
                    "value": 52
                }, 
                "4284893193": {
                    "maximum": 18, 
                    "minimum": 18, 
                    "statHash": 4284893193, 
                    "value": 18
                }, 
                "943549884": {
                    "maximum": 25, 
                    "minimum": 25, 
                    "statHash": 943549884, 
                    "value": 25
                }
            }, 
            "exclusivity": 0, 
            "expansionIndex": 0, 
            "level": 48, 
            "maxLevelRequired": 40, 
            "maxQuality": 0, 
            "minLevelRequired": 40, 
            "minQuality": 0, 
            "sourceHashes": [
                941581325, 
                460228854
            ]
        }
    ], 
    "specialItemType": 0, 
    "statGroupHash": 660767731, 
    "stats": {
        "1345609583": {
            "maximum": 25, 
            "minimum": 15, 
            "statHash": 1345609583, 
            "value": 25
        }, 
        "155624089": {
            "maximum": 76, 
            "minimum": 58, 
            "statHash": 155624089, 
            "value": 66
        }, 
        "1931675084": {
            "maximum": 70, 
            "minimum": 70, 
            "statHash": 1931675084, 
            "value": 70
        }, 
        "2391494160": {
            "maximum": 48, 
            "minimum": 45, 
            "statHash": 2391494160, 
            "value": 45
        }, 
        "2523465841": {
            "maximum": 45, 
            "minimum": 30, 
            "statHash": 2523465841, 
            "value": 30
        }, 
        "2715839340": {
            "maximum": 70, 
            "minimum": 50, 
            "statHash": 2715839340, 
            "value": 50
        }, 
        "3555269338": {
            "maximum": 20, 
            "minimum": 20, 
            "statHash": 3555269338, 
            "value": 20
        }, 
        "3614673599": {
            "maximum": 60, 
            "minimum": 60, 
            "statHash": 3614673599, 
            "value": 60
        }, 
        "368428387": {
            "maximum": 400, 
            "minimum": 280, 
            "statHash": 368428387, 
            "value": 380
        }, 
        "3871231066": {
            "maximum": 1, 
            "minimum": 1, 
            "statHash": 3871231066, 
            "value": 1
        }, 
        "4188031367": {
            "maximum": 59, 
            "minimum": 52, 
            "statHash": 4188031367, 
            "value": 52
        }, 
        "4284893193": {
            "maximum": 18, 
            "minimum": 18, 
            "statHash": 4284893193, 
            "value": 18
        }, 
        "943549884": {
            "maximum": 25, 
            "minimum": 25, 
            "statHash": 943549884, 
            "value": 25
        }
    }, 
    "talentGridHash": 514425958, 
    "tierType": 6, 
    "tierTypeName": "Exotic", 
    "tooltipStyle": "", 
    "uniquenessHash": 3671135542, 
    "values": {}
}