{
    "actionName": "Dismantle", 
    "allowActions": true, 
    "bountyResetUnlockHash": 0, 
    "bucketTypeHash": 1498876634, 
    "classType": 3, 
    "deleteOnAction": true, 
    "equippable": true, 
    "equippingBlock": {
        "arrangements": [
            {
                "classHash": 0, 
                "gearArtArrangementIndex": 3326
            }
        ], 
        "customDyeExpression": {
            "steps": []
        }, 
        "customDyes": [], 
        "defaultDyes": [], 
        "gearArtArrangementIndex": 3326, 
        "lockedDyes": [
            {
                "channelHash": 1667433279, 
                "dyeHash": 767405839
            }, 
            {
                "channelHash": 1667433278, 
                "dyeHash": 2338885336
            }
        ], 
        "weaponPatternHash": 279927711, 
        "weaponSandboxPatternIndex": 84
    }, 
    "exclusive": 0, 
    "hasAction": true, 
    "hasGeometry": true, 
    "hash": 3491886959, 
    "icon": "/common/destiny_content/icons/19a8973bbb2aa4bbab4a8c6137dc13e1.jpg", 
    "index": 0, 
    "instanced": true, 
    "itemCategoryHashes": [
        1, 
        2, 
        8
    ], 
    "itemDescription": "Balanced. Targeted. Empowered. SUROS.", 
    "itemHash": 3491886959, 
    "itemIndex": 0, 
    "itemLevels": [
        0
    ], 
    "itemName": "SUROS DIS-43", 
    "itemSubType": 14, 
    "itemType": 3, 
    "itemTypeName": "Scout Rifle", 
    "maxStackSize": 1, 
    "needsFullCompletion": false, 
    "nonTransferrable": false, 
    "objectiveHashes": [], 
    "perkHashes": [
        1922690640
    ], 
    "primaryBaseStatHash": 368428387, 
    "qualityLevel": 0, 
    "questTrackingUnlockValueHash": 0, 
    "questlineItemHash": 0, 
    "rewardItemHash": 0, 
    "secondaryIcon": "/common/destiny_content/icons/7e05b9b89c2ee02c6025f5b232a15a9e.png", 
    "setItemHashes": [], 
    "sourceHashes": [], 
    "sources": [
        {
            "computedStats": {
                "1240592695": {
                    "maximum": 100, 
                    "minimum": 53, 
                    "statHash": 1240592695, 
                    "value": 77
                }, 
                "1345609583": {
                    "maximum": 66, 
                    "minimum": 61, 
                    "statHash": 1345609583, 
                    "value": 61
                }, 
                "155624089": {
                    "maximum": 99, 
                    "minimum": 15, 
                    "statHash": 155624089, 
                    "value": 48
                }, 
                "1931675084": {
                    "maximum": 50, 
                    "minimum": 50, 
                    "statHash": 1931675084, 
                    "value": 50
                }, 
                "2391494160": {
                    "maximum": 37, 
                    "minimum": 34, 
                    "statHash": 2391494160, 
                    "value": 34
                }, 
                "2715839340": {
                    "maximum": 80, 
                    "minimum": 80, 
                    "statHash": 2715839340, 
                    "value": 80
                }, 
                "3555269338": {
                    "maximum": 25, 
                    "minimum": 20, 
                    "statHash": 3555269338, 
                    "value": 20
                }, 
                "368428387": {
                    "maximum": 310, 
                    "minimum": 290, 
                    "statHash": 368428387, 
                    "value": 290
                }, 
                "3871231066": {
                    "maximum": 23, 
                    "minimum": 13, 
                    "statHash": 3871231066, 
                    "value": 19
                }, 
                "4043523819": {
                    "maximum": 48, 
                    "minimum": 48, 
                    "statHash": 4043523819, 
                    "value": 48
                }, 
                "4188031367": {
                    "maximum": 80, 
                    "minimum": 30, 
                    "statHash": 4188031367, 
                    "value": 45
                }, 
                "4284893193": {
                    "maximum": 37, 
                    "minimum": 37, 
                    "statHash": 4284893193, 
                    "value": 37
                }, 
                "943549884": {
                    "maximum": 89, 
                    "minimum": 34, 
                    "statHash": 943549884, 
                    "value": 39
                }
            }, 
            "exclusivity": 0, 
            "expansionIndex": 0, 
            "level": 49, 
            "maxLevelRequired": 40, 
            "maxQuality": 20, 
            "minLevelRequired": 40, 
            "minQuality": 0, 
            "sourceHashes": [], 
            "spawnIndexes": [
                105, 
                106, 
                107, 
                108, 
                109, 
                110, 
                111, 
                112, 
                113, 
                114, 
                115, 
                116, 
                117, 
                118, 
                119, 
                120, 
                121, 
                122, 
                123, 
                124, 
                125
            ]
        }, 
        {
            "computedStats": {
                "1240592695": {
                    "maximum": 100, 
                    "minimum": 53, 
                    "statHash": 1240592695, 
                    "value": 77
                }, 
                "1345609583": {
                    "maximum": 66, 
                    "minimum": 61, 
                    "statHash": 1345609583, 
                    "value": 61
                }, 
                "155624089": {
                    "maximum": 99, 
                    "minimum": 15, 
                    "statHash": 155624089, 
                    "value": 48
                }, 
                "1931675084": {
                    "maximum": 50, 
                    "minimum": 50, 
                    "statHash": 1931675084, 
                    "value": 50
                }, 
                "2391494160": {
                    "maximum": 36, 
                    "minimum": 33, 
                    "statHash": 2391494160, 
                    "value": 33
                }, 
                "2715839340": {
                    "maximum": 80, 
                    "minimum": 80, 
                    "statHash": 2715839340, 
                    "value": 80
                }, 
                "3555269338": {
                    "maximum": 25, 
                    "minimum": 20, 
                    "statHash": 3555269338, 
                    "value": 20
                }, 
                "368428387": {
                    "maximum": 300, 
                    "minimum": 280, 
                    "statHash": 368428387, 
                    "value": 280
                }, 
                "3871231066": {
                    "maximum": 23, 
                    "minimum": 13, 
                    "statHash": 3871231066, 
                    "value": 19
                }, 
                "4043523819": {
                    "maximum": 48, 
                    "minimum": 48, 
                    "statHash": 4043523819, 
                    "value": 48
                }, 
                "4188031367": {
                    "maximum": 80, 
                    "minimum": 30, 
                    "statHash": 4188031367, 
                    "value": 45
                }, 
                "4284893193": {
                    "maximum": 37, 
                    "minimum": 37, 
                    "statHash": 4284893193, 
                    "value": 37
                }, 
                "943549884": {
                    "maximum": 89, 
                    "minimum": 34, 
                    "statHash": 943549884, 
                    "value": 39
                }
            }, 
            "exclusivity": 0, 
            "expansionIndex": 0, 
            "level": 48, 
            "maxLevelRequired": 40, 
            "maxQuality": 20, 
            "minLevelRequired": 40, 
            "minQuality": 0, 
            "sourceHashes": [], 
            "spawnIndexes": [
                0, 
                85, 
                86, 
                87, 
                88, 
                89, 
                90, 
                91, 
                92, 
                93, 
                94, 
                95, 
                96, 
                97, 
                98, 
                99, 
                100, 
                101, 
                102, 
                103, 
                104
            ]
        }, 
        {
            "computedStats": {
                "1240592695": {
                    "maximum": 100, 
                    "minimum": 53, 
                    "statHash": 1240592695, 
                    "value": 77
                }, 
                "1345609583": {
                    "maximum": 66, 
                    "minimum": 61, 
                    "statHash": 1345609583, 
                    "value": 61
                }, 
                "155624089": {
                    "maximum": 99, 
                    "minimum": 15, 
                    "statHash": 155624089, 
                    "value": 48
                }, 
                "1931675084": {
                    "maximum": 50, 
                    "minimum": 50, 
                    "statHash": 1931675084, 
                    "value": 50
                }, 
                "2391494160": {
                    "maximum": 34, 
                    "minimum": 32, 
                    "statHash": 2391494160, 
                    "value": 32
                }, 
                "2715839340": {
                    "maximum": 80, 
                    "minimum": 80, 
                    "statHash": 2715839340, 
                    "value": 80
                }, 
                "3555269338": {
                    "maximum": 25, 
                    "minimum": 20, 
                    "statHash": 3555269338, 
                    "value": 20
                }, 
                "368428387": {
                    "maximum": 290, 
                    "minimum": 270, 
                    "statHash": 368428387, 
                    "value": 270
                }, 
                "3871231066": {
                    "maximum": 23, 
                    "minimum": 13, 
                    "statHash": 3871231066, 
                    "value": 19
                }, 
                "4043523819": {
                    "maximum": 48, 
                    "minimum": 48, 
                    "statHash": 4043523819, 
                    "value": 48
                }, 
                "4188031367": {
                    "maximum": 80, 
                    "minimum": 30, 
                    "statHash": 4188031367, 
                    "value": 45
                }, 
                "4284893193": {
                    "maximum": 37, 
                    "minimum": 37, 
                    "statHash": 4284893193, 
                    "value": 37
                }, 
                "943549884": {
                    "maximum": 89, 
                    "minimum": 34, 
                    "statHash": 943549884, 
                    "value": 39
                }
            }, 
            "exclusivity": 0, 
            "expansionIndex": 0, 
            "level": 47, 
            "maxLevelRequired": 40, 
            "maxQuality": 20, 
            "minLevelRequired": 40, 
            "minQuality": 0, 
            "sourceHashes": [], 
            "spawnIndexes": [
                64, 
                65, 
                66, 
                67, 
                68, 
                69, 
                70, 
                71, 
                72, 
                73, 
                74, 
                75, 
                76, 
                77, 
                78, 
                79, 
                80, 
                81, 
                82, 
                83, 
                84
            ]
        }, 
        {
            "computedStats": {
                "1240592695": {
                    "maximum": 100, 
                    "minimum": 53, 
                    "statHash": 1240592695, 
                    "value": 77
                }, 
                "1345609583": {
                    "maximum": 66, 
                    "minimum": 61, 
                    "statHash": 1345609583, 
                    "value": 61
                }, 
                "155624089": {
                    "maximum": 99, 
                    "minimum": 15, 
                    "statHash": 155624089, 
                    "value": 48
                }, 
                "1931675084": {
                    "maximum": 50, 
                    "minimum": 50, 
                    "statHash": 1931675084, 
                    "value": 50
                }, 
                "2391494160": {
                    "maximum": 33, 
                    "minimum": 31, 
                    "statHash": 2391494160, 
                    "value": 31
                }, 
                "2715839340": {
                    "maximum": 80, 
                    "minimum": 80, 
                    "statHash": 2715839340, 
                    "value": 80
                }, 
                "3555269338": {
                    "maximum": 25, 
                    "minimum": 20, 
                    "statHash": 3555269338, 
                    "value": 20
                }, 
                "368428387": {
                    "maximum": 280, 
                    "minimum": 260, 
                    "statHash": 368428387, 
                    "value": 260
                }, 
                "3871231066": {
                    "maximum": 23, 
                    "minimum": 13, 
                    "statHash": 3871231066, 
                    "value": 19
                }, 
                "4043523819": {
                    "maximum": 48, 
                    "minimum": 48, 
                    "statHash": 4043523819, 
                    "value": 48
                }, 
                "4188031367": {
                    "maximum": 80, 
                    "minimum": 30, 
                    "statHash": 4188031367, 
                    "value": 45
                }, 
                "4284893193": {
                    "maximum": 37, 
                    "minimum": 37, 
                    "statHash": 4284893193, 
                    "value": 37
                }, 
                "943549884": {
                    "maximum": 89, 
                    "minimum": 34, 
                    "statHash": 943549884, 
                    "value": 39
                }
            }, 
            "exclusivity": 0, 
            "expansionIndex": 0, 
            "level": 46, 
            "maxLevelRequired": 40, 
            "maxQuality": 20, 
            "minLevelRequired": 40, 
            "minQuality": 0, 
            "sourceHashes": [], 
            "spawnIndexes": [
                43, 
                44, 
                45, 
                46, 
                47, 
                48, 
                49, 
                50, 
                51, 
                52, 
                53, 
                54, 
                55, 
                56, 
                57, 
                58, 
                59, 
                60, 
                61, 
                62, 
                63
            ]
        }, 
        {
            "computedStats": {
                "1240592695": {
                    "maximum": 100, 
                    "minimum": 53, 
                    "statHash": 1240592695, 
                    "value": 77
                }, 
                "1345609583": {
                    "maximum": 66, 
                    "minimum": 61, 
                    "statHash": 1345609583, 
                    "value": 61
                }, 
                "155624089": {
                    "maximum": 99, 
                    "minimum": 15, 
                    "statHash": 155624089, 
                    "value": 48
                }, 
                "1931675084": {
                    "maximum": 50, 
                    "minimum": 50, 
                    "statHash": 1931675084, 
                    "value": 50
                }, 
                "2391494160": {
                    "maximum": 32, 
                    "minimum": 30, 
                    "statHash": 2391494160, 
                    "value": 30
                }, 
                "2715839340": {
                    "maximum": 80, 
                    "minimum": 80, 
                    "statHash": 2715839340, 
                    "value": 80
                }, 
                "3555269338": {
                    "maximum": 25, 
                    "minimum": 20, 
                    "statHash": 3555269338, 
                    "value": 20
                }, 
                "368428387": {
                    "maximum": 270, 
                    "minimum": 250, 
                    "statHash": 368428387, 
                    "value": 250
                }, 
                "3871231066": {
                    "maximum": 23, 
                    "minimum": 13, 
                    "statHash": 3871231066, 
                    "value": 19
                }, 
                "4043523819": {
                    "maximum": 48, 
                    "minimum": 48, 
                    "statHash": 4043523819, 
                    "value": 48
                }, 
                "4188031367": {
                    "maximum": 80, 
                    "minimum": 30, 
                    "statHash": 4188031367, 
                    "value": 45
                }, 
                "4284893193": {
                    "maximum": 37, 
                    "minimum": 37, 
                    "statHash": 4284893193, 
                    "value": 37
                }, 
                "943549884": {
                    "maximum": 89, 
                    "minimum": 34, 
                    "statHash": 943549884, 
                    "value": 39
                }
            }, 
            "exclusivity": 0, 
            "expansionIndex": 0, 
            "level": 45, 
            "maxLevelRequired": 40, 
            "maxQuality": 20, 
            "minLevelRequired": 40, 
            "minQuality": 0, 
            "sourceHashes": [], 
            "spawnIndexes": [
                22, 
                23, 
                24, 
                25, 
                26, 
                27, 
                28, 
                29, 
                30, 
                31, 
                32, 
                33, 
                34, 
                35, 
                36, 
                37, 
                38, 
                39, 
                40, 
                41, 
                42
            ]
        }, 
        {
            "computedStats": {
                "1240592695": {
                    "maximum": 100, 
                    "minimum": 53, 
                    "statHash": 1240592695, 
                    "value": 77
                }, 
                "1345609583": {
                    "maximum": 66, 
                    "minimum": 61, 
                    "statHash": 1345609583, 
                    "value": 61
                }, 
                "155624089": {
                    "maximum": 99, 
                    "minimum": 15, 
                    "statHash": 155624089, 
                    "value": 48
                }, 
                "1931675084": {
                    "maximum": 50, 
                    "minimum": 50, 
                    "statHash": 1931675084, 
                    "value": 50
                }, 
                "2391494160": {
                    "maximum": 31, 
                    "minimum": 28, 
                    "statHash": 2391494160, 
                    "value": 28
                }, 
                "2715839340": {
                    "maximum": 80, 
                    "minimum": 80, 
                    "statHash": 2715839340, 
                    "value": 80
                }, 
                "3555269338": {
                    "maximum": 25, 
                    "minimum": 20, 
                    "statHash": 3555269338, 
                    "value": 20
                }, 
                "368428387": {
                    "maximum": 260, 
                    "minimum": 240, 
                    "statHash": 368428387, 
                    "value": 240
                }, 
                "3871231066": {
                    "maximum": 23, 
                    "minimum": 13, 
                    "statHash": 3871231066, 
                    "value": 19
                }, 
                "4043523819": {
                    "maximum": 48, 
                    "minimum": 48, 
                    "statHash": 4043523819, 
                    "value": 48
                }, 
                "4188031367": {
                    "maximum": 80, 
                    "minimum": 30, 
                    "statHash": 4188031367, 
                    "value": 45
                }, 
                "4284893193": {
                    "maximum": 37, 
                    "minimum": 37, 
                    "statHash": 4284893193, 
                    "value": 37
                }, 
                "943549884": {
                    "maximum": 89, 
                    "minimum": 34, 
                    "statHash": 943549884, 
                    "value": 39
                }
            }, 
            "exclusivity": 0, 
            "expansionIndex": 0, 
            "level": 44, 
            "maxLevelRequired": 40, 
            "maxQuality": 20, 
            "minLevelRequired": 40, 
            "minQuality": 0, 
            "sourceHashes": [], 
            "spawnIndexes": [
                1, 
                2, 
                3, 
                4, 
                5, 
                6, 
                7, 
                8, 
                9, 
                10, 
                11, 
                12, 
                13, 
                14, 
                15, 
                16, 
                17, 
                18, 
                19, 
                20, 
                21
            ]
        }
    ], 
    "specialItemType": 0, 
    "statGroupHash": 2453149525, 
    "stats": {
        "1240592695": {
            "maximum": 100, 
            "minimum": 53, 
            "statHash": 1240592695, 
            "value": 77
        }, 
        "1345609583": {
            "maximum": 66, 
            "minimum": 61, 
            "statHash": 1345609583, 
            "value": 61
        }, 
        "155624089": {
            "maximum": 99, 
            "minimum": 15, 
            "statHash": 155624089, 
            "value": 48
        }, 
        "1931675084": {
            "maximum": 50, 
            "minimum": 50, 
            "statHash": 1931675084, 
            "value": 50
        }, 
        "2391494160": {
            "maximum": 37, 
            "minimum": 34, 
            "statHash": 2391494160, 
            "value": 34
        }, 
        "2715839340": {
            "maximum": 80, 
            "minimum": 80, 
            "statHash": 2715839340, 
            "value": 80
        }, 
        "3555269338": {
            "maximum": 25, 
            "minimum": 20, 
            "statHash": 3555269338, 
            "value": 20
        }, 
        "368428387": {
            "maximum": 310, 
            "minimum": 240, 
            "statHash": 368428387, 
            "value": 290
        }, 
        "3871231066": {
            "maximum": 23, 
            "minimum": 13, 
            "statHash": 3871231066, 
            "value": 19
        }, 
        "4043523819": {
            "maximum": 48, 
            "minimum": 48, 
            "statHash": 4043523819, 
            "value": 48
        }, 
        "4188031367": {
            "maximum": 80, 
            "minimum": 30, 
            "statHash": 4188031367, 
            "value": 45
        }, 
        "4284893193": {
            "maximum": 37, 
            "minimum": 37, 
            "statHash": 4284893193, 
            "value": 37
        }, 
        "943549884": {
            "maximum": 89, 
            "minimum": 34, 
            "statHash": 943549884, 
            "value": 39
        }
    }, 
    "talentGridHash": 1415170625, 
    "tierType": 5, 
    "tierTypeName": "Legendary", 
    "uniquenessHash": 2166136261, 
    "values": {}
}