{
    "actionName": "Dismantle", 
    "allowActions": true, 
    "bountyResetUnlockHash": 0, 
    "bucketTypeHash": 1498876634, 
    "classType": 3, 
    "damageTypes": [
        1
    ], 
    "deleteOnAction": true, 
    "equippable": true, 
    "equippingBlock": {
        "arrangements": [
            {
                "classHash": 0, 
                "gearArtArrangementIndex": 2347
            }
        ], 
        "customDyeExpression": {
            "steps": []
        }, 
        "customDyes": [], 
        "defaultDyes": [], 
        "equipmentSlotHash": 1498876634, 
        "gearArtArrangementIndex": 2347, 
        "lockedDyes": [
            {
                "channelHash": 1667433279, 
                "dyeHash": 3405750372
            }, 
            {
                "channelHash": 1667433278, 
                "dyeHash": 2642259659
            }
        ], 
        "weaponPatternHash": 4020227280, 
        "weaponSandboxPatternIndex": 9
    }, 
    "exclusive": 0, 
    "hasAction": true, 
    "hasGeometry": true, 
    "hasIcon": true, 
    "hash": 4075571038, 
    "icon": "/common/destiny_content/icons/20968e3d9dd7a15ad5f4466f4a031ed8.jpg", 
    "index": 0, 
    "instanced": true, 
    "itemCategoryHashes": [
        1, 
        2, 
        8
    ], 
    "itemDescription": "Semi-automatic rifle. This is a marksman's design, built for precision.", 
    "itemHash": 4075571038, 
    "itemIndex": 0, 
    "itemLevels": [
        0
    ], 
    "itemName": "Trax Callum I", 
    "itemSubType": 14, 
    "itemType": 3, 
    "itemTypeName": "Scout Rifle", 
    "maxStackSize": 1, 
    "needsFullCompletion": false, 
    "nonTransferrable": false, 
    "objectiveHashes": [], 
    "perkHashes": [
        3487780612
    ], 
    "primaryBaseStatHash": 368428387, 
    "qualityLevel": 5, 
    "questTrackingUnlockValueHash": 0, 
    "questlineItemHash": 0, 
    "redacted": false, 
    "rewardItemHash": 0, 
    "secondaryIcon": "/img/misc/missing_icon.png", 
    "setItemHashes": [], 
    "showActiveNodesInTooltip": false, 
    "sourceHashes": [
        299200664, 
        1920307024
    ], 
    "sources": [
        {
            "computedStats": {
                "1240592695": {
                    "maximum": 62, 
                    "minimum": 62, 
                    "statHash": 1240592695, 
                    "value": 62
                }, 
                "1345609583": {
                    "maximum": 33, 
                    "minimum": 33, 
                    "statHash": 1345609583, 
                    "value": 33
                }, 
                "155624089": {
                    "maximum": 40, 
                    "minimum": 40, 
                    "statHash": 155624089, 
                    "value": 40
                }, 
                "1931675084": {
                    "maximum": 30, 
                    "minimum": 30, 
                    "statHash": 1931675084, 
                    "value": 30
                }, 
                "2391494160": {
                    "maximum": 1, 
                    "minimum": 1, 
                    "statHash": 2391494160, 
                    "value": 1
                }, 
                "2715839340": {
                    "maximum": 72, 
                    "minimum": 72, 
                    "statHash": 2715839340, 
                    "value": 72
                }, 
                "3555269338": {
                    "maximum": 20, 
                    "minimum": 20, 
                    "statHash": 3555269338, 
                    "value": 20
                }, 
                "368428387": {
                    "maximum": 12, 
                    "minimum": 12, 
                    "statHash": 368428387, 
                    "value": 12
                }, 
                "3871231066": {
                    "maximum": 13, 
                    "minimum": 13, 
                    "statHash": 3871231066, 
                    "value": 13
                }, 
                "4043523819": {
                    "maximum": 48, 
                    "minimum": 48, 
                    "statHash": 4043523819, 
                    "value": 48
                }, 
                "4188031367": {
                    "maximum": 54, 
                    "minimum": 54, 
                    "statHash": 4188031367, 
                    "value": 54
                }, 
                "4284893193": {
                    "maximum": 37, 
                    "minimum": 37, 
                    "statHash": 4284893193, 
                    "value": 37
                }, 
                "943549884": {
                    "maximum": 27, 
                    "minimum": 27, 
                    "statHash": 943549884, 
                    "value": 27
                }
            }, 
            "exclusivity": 0, 
            "expansionIndex": 0, 
            "level": 2, 
            "maxLevelRequired": 2, 
            "maxQuality": 5, 
            "minLevelRequired": 2, 
            "minQuality": 5, 
            "sourceHashes": [
                299200664, 
                1920307024
            ]
        }
    ], 
    "specialItemType": 0, 
    "statGroupHash": 2453149525, 
    "stats": {
        "1240592695": {
            "maximum": 62, 
            "minimum": 62, 
            "statHash": 1240592695, 
            "value": 62
        }, 
        "1345609583": {
            "maximum": 33, 
            "minimum": 33, 
            "statHash": 1345609583, 
            "value": 33
        }, 
        "155624089": {
            "maximum": 40, 
            "minimum": 40, 
            "statHash": 155624089, 
            "value": 40
        }, 
        "1931675084": {
            "maximum": 30, 
            "minimum": 30, 
            "statHash": 1931675084, 
            "value": 30
        }, 
        "2391494160": {
            "maximum": 1, 
            "minimum": 1, 
            "statHash": 2391494160, 
            "value": 1
        }, 
        "2715839340": {
            "maximum": 72, 
            "minimum": 72, 
            "statHash": 2715839340, 
            "value": 72
        }, 
        "3555269338": {
            "maximum": 20, 
            "minimum": 20, 
            "statHash": 3555269338, 
            "value": 20
        }, 
        "368428387": {
            "maximum": 12, 
            "minimum": 12, 
            "statHash": 368428387, 
            "value": 12
        }, 
        "3871231066": {
            "maximum": 13, 
            "minimum": 13, 
            "statHash": 3871231066, 
            "value": 13
        }, 
        "4043523819": {
            "maximum": 48, 
            "minimum": 48, 
            "statHash": 4043523819, 
            "value": 48
        }, 
        "4188031367": {
            "maximum": 54, 
            "minimum": 54, 
            "statHash": 4188031367, 
            "value": 54
        }, 
        "4284893193": {
            "maximum": 37, 
            "minimum": 37, 
            "statHash": 4284893193, 
            "value": 37
        }, 
        "943549884": {
            "maximum": 27, 
            "minimum": 27, 
            "statHash": 943549884, 
            "value": 27
        }
    }, 
    "talentGridHash": 747907260, 
    "tierType": 2, 
    "tierTypeName": "Common", 
    "tooltipStyle": "", 
    "uniquenessHash": 2166136261, 
    "values": {}
}